pylite/__init__.py
pylite/__main__.py
pylite/ast_nodes.py
pylite/builtins.py
pylite/cli.py
pylite/environment.py
pylite/error_handler.py
pylite/interpreter.py
pylite/lexer.py
pylite/parser.py
pylite/tokens.py
pylite/types.py
pylite/assets/sounds/click.wav
pylite/modules/__init__.py
pylite/modules/sound_module.py
pylite/modules/turtle_module.py
tests/__init__.py
tests/test_integration.py
tests/test_interpreter.py
tests/test_lexer.py
tests/test_parser.py
tests/test_sound.py
py_lite_edu-0.1.5.dist-info/LICENSE
py_lite_edu-0.1.5.dist-info/METADATA
py_lite_edu-0.1.5.dist-info/WHEEL
py_lite_edu-0.1.5.dist-info/entry_points.txt
py_lite_edu-0.1.5.dist-info/top_level.txt
py_lite_edu-0.1.5.dist-info/RECORD
