Metadata-Version: 2.1
Name: py-lite-edu
Version: 0.1.5
Summary: Упрощённый Python для обучения детей программированию
Home-page: https://github.com/QueenDekim/pylite
Author: DekimDev
Author-email: collins.vv.dev@gmail.com
Classifier: Development Status :: 3 - Alpha
Classifier: Intended Audience :: Education
Classifier: License :: OSI Approved :: MIT License
Classifier: Operating System :: OS Independent
Classifier: Programming Language :: Python :: 3
Classifier: Programming Language :: Python :: 3.8
Classifier: Programming Language :: Python :: 3.9
Classifier: Programming Language :: Python :: 3.10
Classifier: Programming Language :: Python :: 3.11
Classifier: Topic :: Education
Classifier: Topic :: Software Development :: Interpreters
Requires-Python: >=3.8
License-File: LICENSE
Requires-Dist: PyQt5
Requires-Dist: pygame
